{
  "entradas": {
    "center": {
      "chunk": "0",
      "pos": [400,400],
      "adress": [0,0]
    },
    "17": {"chunk": "665","pos": [400,397],"adress": [17,-1]},
    "16": {"chunk": "664","pos": [400,397],"adress": [16,-1]},
    "15": {"chunk": "663","pos": [400,397],"adress": [15,-1]},
    "14": {"chunk": "662","pos": [400,397],"adress": [14,-1]},
    "13": {"chunk": "661","pos": [400,397],"adress": [13,-1]},
    "12": {"chunk": "660","pos": [400,397],"adress": [12,-1]},
    "11": {"chunk": "659","pos": [400,397],"adress": [11,-1]},
    "10": {"chunk": "658","pos": [400,397],"adress": [10,-1]},
    "9": {"chunk": "657","pos": [400,397],"adress": [9,-1]},
    "8": {"chunk": "656","pos": [400,397],"adress": [8,-1]},
    "7": {"chunk": "655","pos": [400,397],"adress": [7,-1]},
    "6": {"chunk": "654","pos": [400,397],"adress": [6,-1]},
    "5": {"chunk": "653","pos": [400,397],"adress": [5,-1]},
    "4": {"chunk": "652","pos": [400,397],"adress": [4,-1]},
    "3": {"chunk": "651","pos": [400,397],"adress": [3,-1]},
    "2": {"chunk": "650","pos": [400,397],"adress": [2,-1]},
    "1": {"chunk": "649","pos": [400,397],"adress": [1,-1]},
    "0": {"chunk": "648","pos": [400,397],"adress": [0,-1]},
    "35": {"chunk": "683","pos": [400,397],"adress": [35,-1]},
    "34": {"chunk": "682","pos": [400,397],"adress": [34,-1]},
    "33": {"chunk": "681","pos": [400,397],"adress": [33,-1]},
    "32": {"chunk": "680","pos": [400,397],"adress": [32,-1]},
    "31": {"chunk": "679","pos": [400,397],"adress": [31,-1]},
    "30": {"chunk": "678","pos": [400,397],"adress": [30,-1]},
    "29": {"chunk": "677","pos": [400,397],"adress": [29,-1]},
    "28": {"chunk": "676","pos": [400,397],"adress": [28,-1]},
    "27": {"chunk": "675","pos": [400,397],"adress": [27,-1]},
    "26": {"chunk": "674","pos": [400,397],"adress": [26,-1]},
    "25": {"chunk": "673","pos": [400,397],"adress": [25,-1]},
    "24": {"chunk": "672","pos": [400,397],"adress": [24,-1]},
    "23": {"chunk": "671","pos": [400,397],"adress": [23,-1]},
    "22": {"chunk": "670","pos": [400,397],"adress": [22,-1]},
    "21": {"chunk": "669","pos": [400,397],"adress": [21,-1]},
    "20": {"chunk": "668","pos": [400,397],"adress": [20,-1]},
    "19": {"chunk": "667","pos": [400,397],"adress": [19,-1]},
    "18": {"chunk": "666","pos": [400,397],"adress": [18,-1]},
    "629": {"chunk": "701","pos": [400,397],"adress": [17,18]},
    "628": {"chunk": "700","pos": [400,397],"adress": [16,18]},
    "627": {"chunk": "699","pos": [400,397],"adress": [15,18]},
    "626": {"chunk": "698","pos": [400,397],"adress": [14,18]},
    "625": {"chunk": "697","pos": [400,397],"adress": [13,18]},
    "624": {"chunk": "696","pos": [400,397],"adress": [12,18]},
    "623": {"chunk": "695","pos": [400,397],"adress": [11,18]},
    "622": {"chunk": "694","pos": [400,397],"adress": [10,18]},
    "621": {"chunk": "693","pos": [400,397],"adress": [9,18]},
    "620": {"chunk": "692","pos": [400,397],"adress": [8,18]},
    "619": {"chunk": "691","pos": [400,397],"adress": [7,18]},
    "618": {"chunk": "690","pos": [400,397],"adress": [6,18]},
    "617": {"chunk": "689","pos": [400,397],"adress": [5,18]},
    "616": {"chunk": "688","pos": [400,397],"adress": [4,18]},
    "615": {"chunk": "687","pos": [400,397],"adress": [3,18]},
    "614": {"chunk": "686","pos": [400,397],"adress": [2,18]},
    "613": {"chunk": "685","pos": [400,397],"adress": [1,18]},
    "612": {"chunk": "684","pos": [400,397],"adress": [0,18]},
    "647": {"chunk": "702","pos": [400,397],"adress": [35,18]},
    "646": {"chunk": "703","pos": [400,397],"adress": [34,18]},
    "645": {"chunk": "704","pos": [400,397],"adress": [33,18]},
    "644": {"chunk": "705","pos": [400,397],"adress": [32,18]},
    "643": {"chunk": "706","pos": [400,397],"adress": [31,18]},
    "642": {"chunk": "707","pos": [400,397],"adress": [30,18]},
    "641": {"chunk": "708","pos": [400,397],"adress": [29,18]},
    "640": {"chunk": "709","pos": [400,397],"adress": [28,18]},
    "639": {"chunk": "710","pos": [400,397],"adress": [27,18]},
    "638": {"chunk": "711","pos": [400,397],"adress": [26,18]},
    "637": {"chunk": "712","pos": [400,397],"adress": [25,18]},
    "636": {"chunk": "713","pos": [400,397],"adress": [24,18]},
    "635": {"chunk": "714","pos": [400,397],"adress": [23,18]},
    "634": {"chunk": "715","pos": [400,397],"adress": [22,18]},
    "633": {"chunk": "716","pos": [400,397],"adress": [21,18]},
    "632": {"chunk": "717","pos": [400,397],"adress": [20,18]},
    "631": {"chunk": "718","pos": [400,397],"adress": [19,18]},
    "630": {"chu<nk": "719","pos": [400,397],"adress": [18,18]}
  },
  "salidas": [
    {
      "stage": "anti-world","chunk_adress": [0,-1],"nombre": "Norte #0",
      "entrada": "000'","direcciones": ["arriba"],"rect": [0,400,800,32]
    },
    {
      "stage": "anti-world","chunk_adress": [1,-1],"nombre": "Norte #1",
      "entrada": "001'","direcciones": ["arriba"],"rect": [0,400,800,32]
    },
    {
      "stage": "anti-world","chunk_adress": [2,-1],"nombre": "Norte #2",
      "entrada": "002'","direcciones": ["arriba"],"rect": [0,400,800,32]
    },
    {
      "stage": "anti-world","chunk_adress": [3,-1],"nombre": "Norte #3",
      "entrada": "003'","direcciones": ["arriba"],"rect": [0,400,800,32]
    },
    {
      "stage": "anti-world","chunk_adress": [4,-1],"nombre": "Norte #4",
      "entrada": "004'","direcciones": ["arriba"],"rect": [0,400,800,32]
    },
    {
      "stage": "anti-world","chunk_adress": [5,-1],"nombre": "Norte #5",
      "entrada": "005'","direcciones": ["arriba"],"rect": [0,400,800,32]
    },
    {
      "stage": "anti-world","chunk_adress": [6,-1],"nombre": "Norte #6",
      "entrada": "006'","direcciones": ["arriba"],"rect": [0,400,800,32]
    },
    {
      "stage": "anti-world","chunk_adress": [7,-1],"nombre": "Norte #7",
      "entrada": "007'","direcciones": ["arriba"],"rect": [0,400,800,32]
    },
    {
      "stage": "anti-world","chunk_adress": [8,-1],"nombre": "Norte #8",
      "entrada": "008'","direcciones": ["arriba"],"rect": [0,400,800,32]
    },
    {
      "stage": "anti-world","chunk_adress": [9,-1],"nombre": "Norte #9",
      "entrada": "009'","direcciones": ["arriba"],"rect": [0,400,800,32]
    },
    {
      "stage": "anti-world","chunk_adress": [10,-1],"nombre": "Norte #10",
      "entrada": "010'","direcciones": ["arriba"],"rect": [0,400,800,32]
    },
    {
      "stage": "anti-world","chunk_adress": [11,-1],"nombre": "Norte #11",
      "entrada": "011'","direcciones": ["arriba"],"rect": [0,400,800,32]
    },
    {
      "stage": "anti-world","chunk_adress": [12,-1],"nombre": "Norte #12",
      "entrada": "012'","direcciones": ["arriba"],"rect": [0,400,800,32]
    },
    {
      "stage": "anti-world","chunk_adress": [13,-1],"nombre": "Norte #13",
      "entrada": "013'","direcciones": ["arriba"],"rect": [0,400,800,32]
    },
    {
      "stage": "anti-world","chunk_adress": [14,-1],"nombre": "Norte #14",
      "entrada": "014'","direcciones": ["arriba"],"rect": [0,400,800,32]
    },
    {
      "stage": "anti-world","chunk_adress": [15,-1],"nombre": "Norte #15",
      "entrada": "015'","direcciones": ["arriba"],"rect": [0,400,800,32]
    },
    {
      "stage": "anti-world","chunk_adress": [16,-1],"nombre": "Norte #16",
      "entrada": "016'","direcciones": ["arriba"],"rect": [0,400,800,32]
    },
    {
      "stage": "anti-world","chunk_adress": [17,-1],"nombre": "Norte #17",
      "entrada": "017'","direcciones": ["arriba"],"rect": [0,400,800,32]
    },
    {
      "stage": "anti-world","chunk_adress": [18,-1],"nombre": "Norte #18",
      "entrada": "018'","direcciones": ["arriba"],"rect": [0,400,800,32]
    },
    {
      "stage": "anti-world","chunk_adress": [19,-1],"nombre": "Norte #19",
      "entrada": "019'","direcciones": ["arriba"],"rect": [0,400,800,32]
    },
    {
      "stage": "anti-world","chunk_adress": [20,-1],"nombre": "Norte #20",
      "entrada": "020'","direcciones": ["arriba"],"rect": [0,400,800,32]
    },
    {
      "stage": "anti-world","chunk_adress": [21,-1],"nombre": "Norte #21",
      "entrada": "021'","direcciones": ["arriba"],"rect": [0,400,800,32]
    },
    {
      "stage": "anti-world","chunk_adress": [22,-1],"nombre": "Norte #22",
      "entrada": "022'","direcciones": ["arriba"],"rect": [0,400,800,32]
    },
    {
      "stage": "anti-world","chunk_adress": [23,-1],"nombre": "Norte #23",
      "entrada": "023'","direcciones": ["arriba"],"rect": [0,400,800,32]
    },
    {
      "stage": "anti-world","chunk_adress": [24,-1],"nombre": "Norte #24",
      "entrada": "024'","direcciones": ["arriba"],"rect": [0,400,800,32]
    },
    {
      "stage": "anti-world","chunk_adress": [25,-1],"nombre": "Norte #25",
      "entrada": "025'","direcciones": ["arriba"],"rect": [0,400,800,32]
    },
    {
      "stage": "anti-world","chunk_adress": [26,-1],"nombre": "Norte #26",
      "entrada": "026'","direcciones": ["arriba"],"rect": [0,400,800,32]
    },
    {
      "stage": "anti-world","chunk_adress": [27,-1],"nombre": "Norte #27",
      "entrada": "027'","direcciones": ["arriba"],"rect": [0,400,800,32]
    },
    {
      "stage": "anti-world","chunk_adress": [28,-1],"nombre": "Norte #28",
      "entrada": "028'","direcciones": ["arriba"],"rect": [0,400,800,32]
    },
    {
      "stage": "anti-world","chunk_adress": [29,-1],"nombre": "Norte #29",
      "entrada": "029'","direcciones": ["arriba"],"rect": [0,400,800,32]
    },
    {
      "stage": "anti-world","chunk_adress": [30,-1],"nombre": "Norte #30",
      "entrada": "030'","direcciones": ["arriba"],"rect": [0,400,800,32]
    },
    {
      "stage": "anti-world","chunk_adress": [31,-1],"nombre": "Norte #31",
      "entrada": "031'","direcciones": ["arriba"],"rect": [0,400,800,32]
    },
    {
      "stage": "anti-world","chunk_adress": [32,-1],"nombre": "Norte #32",
      "entrada": "032'","direcciones": ["arriba"],"rect": [0,400,800,32]
    },
    {
      "stage": "anti-world","chunk_adress": [33,-1],"nombre": "Norte #33",
      "entrada": "033'","direcciones": ["arriba"],"rect": [0,400,800,32]
    },
    {
      "stage": "anti-world","chunk_adress": [34,-1],"nombre": "Norte #34",
      "entrada": "034'","direcciones": ["arriba"],"rect": [0,400,800,32]
    },
    {
      "stage": "anti-world","chunk_adress": [35,-1],"nombre": "Norte #35",
      "entrada": "035'","direcciones": ["arriba"],"rect": [0,400,800,32]
    },
    {
      "stage": "anti-world","chunk_adress": [0,18],"nombre": "Sur #0",
      "entrada": "612'","direcciones": ["abajo"],"rect": [0,400,800,32]
    },
    {
      "stage": "anti-world","chunk_adress": [1,18],"nombre": "Sur #1",
      "entrada": "613'","direcciones": ["abajo"],"rect": [0,400,800,32]
    },
    {
      "stage": "anti-world","chunk_adress": [2,18],"nombre": "Sur #2",
      "entrada": "614'","direcciones": ["abajo"],"rect": [0,400,800,32]
    },
    {
      "stage": "anti-world","chunk_adress": [3,18],"nombre": "Sur #3",
      "entrada": "615'","direcciones": ["abajo"],"rect": [0,400,800,32]
    },
    {
      "stage": "anti-world","chunk_adress": [4,18],"nombre": "Sur #4",
      "entrada": "616'","direcciones": ["abajo"],"rect": [0,400,800,32]
    },
    {
      "stage": "anti-world","chunk_adress": [5,18],"nombre": "Sur #5",
      "entrada": "617'","direcciones": ["abajo"],"rect": [0,400,800,32]
    },
    {
      "stage": "anti-world","chunk_adress": [6,18],"nombre": "Sur #6",
      "entrada": "618'","direcciones": ["abajo"],"rect": [0,400,800,32]
    },
    {
      "stage": "anti-world","chunk_adress": [7,18],"nombre": "Sur #7",
      "entrada": "619'","direcciones": ["abajo"],"rect": [0,400,800,32]
    },
    {
      "stage": "anti-world","chunk_adress": [8,18],"nombre": "Sur #8",
      "entrada": "620'","direcciones": ["abajo"],"rect": [0,400,800,32]
    },
    {
      "stage": "anti-world","chunk_adress": [9,18],"nombre": "Sur #9",
      "entrada": "621'","direcciones": ["abajo"],"rect": [0,400,800,32]
    },
    {
      "stage": "anti-world","chunk_adress": [10,18],"nombre": "Sur #10",
      "entrada": "622'","direcciones": ["abajo"],"rect": [0,400,800,32]
    },
    {
      "stage": "anti-world","chunk_adress": [11,18],"nombre": "Sur #11",
      "entrada": "623'","direcciones": ["abajo"],"rect": [0,400,800,32]
    },
    {
      "stage": "anti-world","chunk_adress": [12,18],"nombre": "Sur #12",
      "entrada": "624'","direcciones": ["abajo"],"rect": [0,400,800,32]
    },
    {
      "stage": "anti-world","chunk_adress": [13,18],"nombre": "Sur #13",
      "entrada": "625'","direcciones": ["abajo"],"rect": [0,400,800,32]
    },
    {
      "stage": "anti-world","chunk_adress": [14,18],"nombre": "Sur #14",
      "entrada": "626'","direcciones": ["abajo"],"rect": [0,400,800,32]
    },
    {
      "stage": "anti-world","chunk_adress": [15,18],"nombre": "Sur #15",
      "entrada": "627'","direcciones": ["abajo"],"rect": [0,400,800,32]
    },
    {
      "stage": "anti-world","chunk_adress": [16,18],"nombre": "Sur #16",
      "entrada": "628'","direcciones": ["abajo"],"rect": [0,400,800,32]
    },
    {
      "stage": "anti-world","chunk_adress": [17,18],"nombre": "Sur #17",
      "entrada": "629'","direcciones": ["abajo"],"rect": [0,400,800,32]
    },
    {
      "stage": "anti-world","chunk_adress": [18,18],"nombre": "Sur #18",
      "entrada": "630'","direcciones": ["abajo"],"rect": [0,400,800,32]
    },
    {
      "stage": "anti-world","chunk_adress": [19,18],"nombre": "Sur #19",
      "entrada": "631'","direcciones": ["abajo"],"rect": [0,400,800,32]
    },
    {
      "stage": "anti-world","chunk_adress": [20,18],"nombre": "Sur #20",
      "entrada": "632'","direcciones": ["abajo"],"rect": [0,400,800,32]
    },
    {
      "stage": "anti-world","chunk_adress": [21,18],"nombre": "Sur #21",
      "entrada": "633'","direcciones": ["abajo"],"rect": [0,400,800,32]
    },
    {
      "stage": "anti-world","chunk_adress": [22,18],"nombre": "Sur #22",
      "entrada": "634'","direcciones": ["abajo"],"rect": [0,400,800,32]
    },
    {
      "stage": "anti-world","chunk_adress": [23,18],"nombre": "Sur #23",
      "entrada": "635'","direcciones": ["abajo"],"rect": [0,400,800,32]
    },
    {
      "stage": "anti-world","chunk_adress": [24,18],"nombre": "Sur #24",
      "entrada": "636'","direcciones": ["abajo"],"rect": [0,400,800,32]
    },
    {
      "stage": "anti-world","chunk_adress": [25,18],"nombre": "Sur #25",
      "entrada": "637'","direcciones": ["abajo"],"rect": [0,400,800,32]
    },
    {
      "stage": "anti-world","chunk_adress": [26,18],"nombre": "Sur #26",
      "entrada": "638'","direcciones": ["abajo"],"rect": [0,400,800,32]
    },
    {
      "stage": "anti-world","chunk_adress": [27,18],"nombre": "Sur #27",
      "entrada": "639'","direcciones": ["abajo"],"rect": [0,400,800,32]
    },
    {
      "stage": "anti-world","chunk_adress": [28,18],"nombre": "Sur #28",
      "entrada": "640'","direcciones": ["abajo"],"rect": [0,400,800,32]
    },
    {
      "stage": "anti-world","chunk_adress": [29,18],"nombre": "Sur #29",
      "entrada": "641'","direcciones": ["abajo"],"rect": [0,400,800,32]
    },
    {
      "stage": "anti-world","chunk_adress": [30,18],"nombre": "Sur #30",
      "entrada": "642'","direcciones": ["abajo"],"rect": [0,400,800,32]
    },
    {
      "stage": "anti-world","chunk_adress": [31,18],"nombre": "Sur #31",
      "entrada": "643'","direcciones": ["abajo"],"rect": [0,400,800,32]
    },
    {
      "stage": "anti-world","chunk_adress": [32,18],"nombre": "Sur #32",
      "entrada": "644'","direcciones": ["abajo"],"rect": [0,400,800,32]
    },
    {
      "stage": "anti-world","chunk_adress": [33,18],"nombre": "Sur #33",
      "entrada": "645'","direcciones": ["abajo"],"rect": [0,400,800,32]
    },
    {
      "stage": "anti-world","chunk_adress": [34,18],"nombre": "Sur #34",
      "entrada": "646'","direcciones": ["abajo"],"rect": [0,400,800,32]
    },
    {
      "stage": "anti-world","chunk_adress": [35,18],"nombre": "Sur #35",
      "entrada": "647'","direcciones": ["abajo"],"rect": [0,400,800,32]
    }
  ],
  "chunks_csv": "world.chunks.csv",
  "props_csv": "world.props.csv",
  "puntos_de_interes_para_la_IA": [],
  "ambiente": "exterior",
  "latitude": 30,
  "longitude": 30
}